package/__init__.py
package/common.py
package/roblang.py
package/socketfunc.py
package/visionfunc.py
Kais_pgm-0.0.1.dist-info/METADATA
Kais_pgm-0.0.1.dist-info/WHEEL
Kais_pgm-0.0.1.dist-info/top_level.txt
Kais_pgm-0.0.1.dist-info/RECORD
